Metadata-Version: 2.1
Name: vaz
Version: 0.0.6
Summary: Testing installation of Package
Home-page: https://github.com/samansiadati/vaz
Author: Saman Siadati
Author-email: siadatisaman@gmail.com
License: MIT
Download-URL: https://github.com/samansiadati/vaz/archive/refs/tags/vaz.tar.gz
Project-URL: Bug Tracker, https://github.com/samansiadati/vaz/issues
Keywords: pandas,manipulation,vaz
Platform: UNKNOWN
Classifier: Development Status :: 3 - Alpha
Classifier: Intended Audience :: Developers
Classifier: Topic :: Software Development :: Documentation
Classifier: License :: OSI Approved :: MIT License
Classifier: Programming Language :: Python :: 3.8
